{
  "$schema": "https://developer.microsoft.com/json-schemas/rush/v5/rush.schema.json",
  "allowMostlyStandardPackageNames": true,
  "approvedPackagesPolicy": {
    "reviewCategories": [
      "production",
      "libraries",
      "tools",
      "prototypes"
    ],
    "ignoredNpmScopes": [
      "@types"
    ]
  },
  "ensureConsistentVersions": true,
  "gitPolicy": {
    "changeLogUpdateCommitMessage": "docs: update changelogs [skip ci]",
    "versionBumpCommitMessage": "chore: bump versions [skip ci]"
  },
  "nodeSupportedVersionRange": ">=12.13.0 <13.0.0 || >=14.15.0 <15.0.0 || >=16.13.0 <17.0.0",
  "pnpmOptions": {
    "strictPeerDependencies": true,
    "useWorkspaces": true
  },
  "pnpmVersion": "6.32.8",
  "projectFolderMaxDepth": 3,
  "projectFolderMinDepth": 2,
  "projects": [
    {
      "packageName": "@just-web/github-pages",
      "projectFolder": "docs/github-pages",
      "reviewCategory": "libraries"
    },
    {
      "packageName": "@just-func/play-solid",
      "projectFolder": "apps/just-func/play-solid",
      "reviewCategory": "production"
    },
    {
      "packageName": "@just-func/play-react",
      "projectFolder": "apps/just-func/play-react",
      "reviewCategory": "production"
    },
    {
      "packageName": "@just-web/platform",
      "projectFolder": "frameworks/platform",
      "reviewCategory": "libraries"
    },
    {
      "packageName": "@just-web/app",
      "projectFolder": "frameworks/app",
      "reviewCategory": "libraries"
    },
    {
      "packageName": "@just-web/contributions",
      "projectFolder": "frameworks/contributions",
      "reviewCategory": "libraries"
    },
    {
      "packageName": "@just-web/errors",
      "projectFolder": "frameworks/errors",
      "reviewCategory": "libraries"
    },
    {
      "packageName": "@just-web/events",
      "projectFolder": "frameworks/events",
      "reviewCategory": "libraries"
    },
    {
      "packageName": "@just-web/format",
      "projectFolder": "frameworks/format",
      "reviewCategory": "libraries"
    },
    {
      "packageName": "@just-web/log",
      "projectFolder": "frameworks/log",
      "reviewCategory": "libraries"
    },
    {
      "packageName": "@just-web/repo-scripts",
      "projectFolder": "tools/repo-scripts",
      "reviewCategory": "libraries"
    },
    {
      "packageName": "@just-web/states",
      "projectFolder": "frameworks/states",
      "reviewCategory": "libraries"
    },
    {
      "packageName": "@just-web/testing",
      "projectFolder": "tools/testing",
      "reviewCategory": "tools"
    },
    {
      "packageName": "@just-web/commands",
      "projectFolder": "frameworks/commands",
      "reviewCategory": "libraries"
    },
    {
      "packageName": "@just-web/react",
      "projectFolder": "libraries/react",
      "reviewCategory": "libraries"
    },
    {
      "packageName": "@just-web/routes",
      "projectFolder": "plugins/routes",
      "reviewCategory": "libraries"
    },
    {
      "packageName": "@just-web/react-commands",
      "projectFolder": "components/react-commands",
      "reviewCategory": "libraries"
    }
  ],
  "repository": {
    "defaultBranch": "main",
    "url": "https://github.com/justland/just-web"
  },
  "rushVersion": "5.66.2",
  "variants": []
}
